RTL/Verificar_módulos/generador_nonce/driver.v
//Init task for clean output signals

task drv_init;
  begin @(posedge clk)//Inicializando registros e enable = 0
	reset_L <= 0;    
	@(posedge clk)
	reset_L <= 1;
	valid = 0;
	@(posedge clk)
	valid = 0;
	@(posedge clk)
	valid = 0;
	@(posedge clk)
	valid = 0;
	@(posedge clk)
	valid = 0;
	@(posedge clk)
	valid = 0;
	@(posedge clk)
	valid = 1;
	@(posedge clk)
	valid = 1;
	@(posedge clk)
	valid = 0;
end
endtask


// task bloque_in_fill;
// begin @(posedge clk)
// 	//bloque_in [127:0] = 128'h3c87edfd24331f6b6c9eca402f9f7d39;
// 																	//cual es?
// 	//bloque_in [127:0] = 128'h397d9f2f40ca9e6c6b1f3324fded873c;
// 	//bloque_in [127:0] = 128'hed18be0f984ae0e2e3128efe0fa23491;
// 	bloque_in [127:0] = 128'h8855c7ac8b73f8f29701eff1ba0f98b3;
// 	// bloque_in [63:32] = $random;
// 	// bloque_in [95:64] = $random;
// 	// bloque_in [127:95] = $random;
// end
// endtask
/////////////////////////////

RTL/Verificar_módulos/generador_nonce/probador.v
// Testbench Code Goes here
`timescale 1ns / 1ps
module probador(
input clk, 
input [7:0] nonce,
output reset_L,
output reg valid
);

reg reset_L;

`include "driver.v"
initial begin

  $dumpfile("test.vcd");
  $dumpvars(0);

  // log = $fopen("tb.log");
//   $fdisplay(log, "time=%5d, Simulation Start", $time); ////////
//   $fdisplay(log, "time=%5d, Starting Reset", $time); ///////
  
  drv_init();
  // bloque_in_fill();
  
  
//   $fdisplay(log, "time=%5d, Reset Completed", $time); /////

//   $fdisplay(log, "time=%5d, Starting Test", $time);
//   checker(ITERATIONS);


//   $fdisplay(log, "time=%5d, Test Completed", $time);
//   $fdisplay(log, "time=%5d, Simulation Completed", $time);
//   $fclose(log);
 #1000 $finish;
end





endmodule

RTL/Verificar_módulos/generador_nonce/generador_nonce.v
`timescale 1ns / 1ps
module generador_nonce (
    input clk,
    input reset_L,
    input valid,
    output reg [23:0] nonce
);
    

    always @(posedge clk) begin
        if (reset_L == 0) begin
            nonce <= 0;
        end
        else begin
           if (valid == 0) begin
               nonce <= $random;
           end 
        end
    end

endmodule

RTL/Verificar_módulos/generador_nonce/clock.v
`timescale 1ns / 1ps
module clock (clk);

output clk;
reg clk;

initial begin
clk = 0;
end

always begin
 #100 clk = !clk;
end

endmodule

RTL/Verificar_módulos/generador_nonce/tbtop.v
// `include "clock.v"

// `include "cmos/cmos_cells.v"
`include "probador.v"
`include "generador_nonce.v"
`include "clock.v"

module tbtop;
/*AUTOWIRE*/
// Beginning of automatic wires (for undeclared instantiated-module outputs)
wire			clk;			// From reloj of clock.v
wire [23:0]		nonce;			// From noncegen of generador_nonce.v
wire			reset_L;		// From tb of probador.v
wire			valid;			// From tb of probador.v
// End of automatics
   clock reloj (/*AUTOINST*/
		// Outputs
		.clk			(clk));

   generador_nonce noncegen (/*AUTOINST*/
			     // Outputs
			     .nonce		(nonce[23:0]),
			     // Inputs
			     .clk		(clk),
			     .reset_L		(reset_L),
			     .valid		(valid));
   
    probador tb (/*AUTOINST*/
		 // Outputs
		 .reset_L		(reset_L),
		 .valid			(valid),
		 // Inputs
		 .clk			(clk),
		 .nonce			(nonce[23:0]));
   

 
endmodule

RTL/Verificar_módulos/generador_nonce/test.vcd
$date
	Mon Jul 12 22:20:10 2021
$end
$version
	Icarus Verilog
$end
$timescale
	1ps
$end
$scope module tbtop $end
$var wire 1 ! valid $end
$var wire 1 " reset_L $end
$var wire 24 # nonce [23:0] $end
$var wire 1 $ clk $end
$scope module noncegen $end
$var wire 1 ! valid $end
$var wire 1 " reset_L $end
$var wire 1 $ clk $end
$var reg 24 % nonce [23:0] $end
$upscope $end
$scope module reloj $end
$var reg 1 $ clk $end
$upscope $end
$scope module tb $end
$var wire 1 $ clk $end
$var wire 8 & nonce [7:0] $end
$var reg 1 " reset_L $end
$var reg 1 ! valid $end
$scope task drv_init $end
$upscope $end
$upscope $end
$upscope $end
$enddefinitions $end
#0
$dumpvars
bx &
bx %
0$
bx #
x"
x!
$end
#100000
0"
1$
#200000
0$
#300000
b0 &
1"
b0 #
b0 %
0!
1$
#400000
0$
#500000
b100100 &
b101010011010100100100 #
b101010011010100100100 %
1$
#600000
0$
#700000
b10000001 &
b100010010101111010000001 #
b100010010101111010000001 %
1$
#800000
0$
#900000
b1001 &
b100001001101011000001001 #
b100001001101011000001001 %
1$
#1000000
0$
#1100000
b1100011 &
b111100000101011001100011 #
b111100000101011001100011 %
1$
#1200000
0$
#1300000
b1101 &
b101110010111101100001101 #
b101110010111101100001101 %
1$
#1400000
0$
#1500000
b10001101 &
b110111111001100110001101 #
b110111111001100110001101 %
1!
1$
#1600000
0$
#1700000
1$
#1800000
0$
#1900000
0!
1$
#2000000
0$
#2100000
b1100101 &
b110000101000010001100101 #
b110000101000010001100101 %
1$
#2200000
0$
#2300000
b10010 &
b1101110101001000010010 #
b1101110101001000010010 %
1$
#2400000
0$
#2500000
b1 &
b111100111110001100000001 #
b111100111110001100000001 %
1$
#2600000
0$
#2700000
b1101 &
b110101111100110100001101 #
b110101111100110100001101 %
1$
