RTL/Verificar_módulos/micro_ucr_hash/driver.v
//Init task for clean output signals

task drv_init;
  begin @(posedge clk)//Inicializando registros e enable = 0
	reset_L <= 0;    
	@(posedge clk)
	  bloque_in [127:0] <=  128'h397d9f2f40ca9e6c6b1f3324fded873c;
     
	@(posedge clk)
	reset_L <= 1;
	@(posedge clk)
	reset_L <= 1;
end
endtask


// task bloque_in_fill;
// begin @(posedge clk)
// 	//bloque_in [127:0] = 128'h3c87edfd24331f6b6c9eca402f9f7d39;
// 																	//cual es?
// 	//bloque_in [127:0] = 128'h397d9f2f40ca9e6c6b1f3324fded873c;
// 	//bloque_in [127:0] = 128'hed18be0f984ae0e2e3128efe0fa23491;
// 	bloque_in [127:0] = 128'h8855c7ac8b73f8f29701eff1ba0f98b3;
// 	// bloque_in [63:32] = $random;
// 	// bloque_in [95:64] = $random;
// 	// bloque_in [127:95] = $random;
// end
// endtask
/////////////////////////////

RTL/Verificar_módulos/micro_ucr_hash/probador.v
// Testbench Code Goes here
`timescale 1ns / 1ps
module probador(
input clk, 
output reset_L,
output fill,
output [127:0] bloque_in,
input [23:0] H
);

reg fill;
reg reset_L;
reg [127:0] bloque_in;

`include "driver.v"
initial begin

  $dumpfile("test.vcd");
  $dumpvars(0);

  // log = $fopen("tb.log");
//   $fdisplay(log, "time=%5d, Simulation Start", $time); ////////
//   $fdisplay(log, "time=%5d, Starting Reset", $time); ///////
  
  drv_init();
  // bloque_in_fill();
  
  
//   $fdisplay(log, "time=%5d, Reset Completed", $time); /////

//   $fdisplay(log, "time=%5d, Starting Test", $time);
//   checker(ITERATIONS);


//   $fdisplay(log, "time=%5d, Test Completed", $time);
//   $fdisplay(log, "time=%5d, Simulation Completed", $time);
//   $fclose(log);
 #10000 $finish;
end





endmodule

RTL/Verificar_módulos/micro_ucr_hash/micro_ucr_hash.v
`timescale 1ns / 1ps
module micro_ucr_hash (input clk, 
                        input reset_L,
                        input [127:0] bloque_in,
                        input fill,
                        output [23:0] H);
//    reg [7:0] bloque [15:0];                                      
    reg [23:0] H;

    reg [7:0] H_0;
    reg [7:0] H_1;
    reg [7:0] H_2;
   
   
    reg [7:0] a;
    reg [7:0] b;
    reg [7:0] c;

    reg [7:0] k;
    reg [7:0] x;

    reg [7:0] W [31:0];

    reg [6:0] count;

    always @(*) begin
        if (reset_L == 0) begin
            W[0] = 0;
            W[1] = 0;
            W[2] = 0;
            W[3] = 0;
            W[4] = 0;
            W[5] = 0;
            W[6] = 0;
            W[7] = 0;
            W[8] = 0;
            W[9] = 0;
            W[10] = 0;
            W[11] = 0;
            W[12] = 0;
            W[13] = 0;
            W[14] = 0;
            W[15] = 0;
            W[16] = 0;
            W[17] = 0;
            W[18] = 0;
            W[19] = 0;
            W[20] = 0;
            W[21] = 0;
            W[22] = 0;
            W[23] = 0;
            W[24] = 0;
            W[25] = 0;
            W[26] = 0;
            W[27] = 0;
            W[28] = 0;
            W[29] = 0;
            W[30] = 0;
            W[31] = 0; 
        end
        else begin
        
            W[0] = bloque_in[7:0];
            W[1] = bloque_in[15:8];
            W[2] = bloque_in[23:16];
            W[3] = bloque_in[31:24];
            W[4] = bloque_in[39:32];
            W[5] = bloque_in[47:40];
            W[6] = bloque_in[55:48];
            W[7] = bloque_in[63:56];
            W[8] = bloque_in[71:64];
            W[9] = bloque_in[79:72];
            W[10] = bloque_in[87:80];
            W[11] = bloque_in[95:88];
            W[12] = bloque_in[103:96];
            W[13] = bloque_in[111:104];
            W[14] = bloque_in[119:112];
            W[15] = bloque_in[127:120];
            W[16] = W[13] | W[7] ^ W[2];
            W[17] = W[14] | W[8] ^ W[3];
            W[18] = W[15] | W[9] ^ W[4];
            W[19] = W[16] | W[10] ^ W[5];
            W[20] = W[17] | W[11] ^ W[6];//     W[i] = W[i - 3] | W[i - 9] ^ W[i - 14];
            W[21] = W[18] | W[12] ^ W[7];
            W[22] = W[19] | W[13] ^ W[8];
            W[23] = W[20] | W[14] ^ W[9];
            W[24] = W[21] | W[15] ^ W[10];
            W[25] = W[22] | W[16] ^ W[11];
            W[26] = W[23] | W[17] ^ W[12];
            W[27] = W[24] | W[18] ^ W[13];
            W[28] = W[25] | W[19] ^ W[14];
            W[29] = W[26] | W[20] ^ W[15];
            W[30] = W[27] | W[21] ^ W[16];
            W[31] = W[28] | W[22] ^ W[17];


                //   W[16] =(W[13] | W[7])^ W[2];
                // W[17] =(W[14] | W[8])^ W[3];
                // W[18] =(W[15] | W[9])^ W[4];
                // W[19] =(W[16] | W[10])^ W[5];
                // W[20] =(W[17] | W[11])^ W[6];//     W[i] =(W[i - 3] | W[i - 9])^ W[i - 14];
                // W[21] =(W[18] | W[12])^ W[7];
                // W[22] =(W[19] | W[13])^ W[8];
                // W[23] =(W[20] | W[14])^ W[9];
                // W[24] =(W[21] | W[15])^ W[10];
                // W[25] =(W[22] | W[16])^ W[11];
                // W[26] =(W[23] | W[17])^ W[12];
                // W[27] =(W[24] | W[18])^ W[13];
                // W[28] =(W[25] | W[19])^ W[14];
                // W[29] =(W[26] | W[20])^ W[15];
                // W[30] =(W[27] | W[21])^ W[16];
                // W[31] =(W[28] | W[22])^ W[17];
        end   
        
    end     

    always @(posedge clk ) begin
       
        if (reset_L == 0) begin
            H <= 0;
            H_0 <= 8'h01;
            H_1 <= 8'h89; 
            H_2 <= 8'hfe;

            a <= 8'h01;
            b <= 8'h89;
            c <= 8'hfe;

            k <= 8'h99;
            x <= (a ^ b);

            count <= 0;
        end
        else begin

            if (count <= 16) begin
                k <= 8'h99;
                x <= a ^ b;
            end 
            else begin
                if (count <= 31) begin
                k <= 8'ha1;
                x <= (a | b);
                end
            end
            if (count < 32) begin //arreglar 32
                a <= (b^c);
                b <= c << 4;
                c <= x + k + W[count];
                count <= count + 1;
            end
            
            if (count == 32) begin
                H [23:16] <= H_0;
                H [15:8] <= H_1;
                H [7:0] <= H_2;
                H_0 <= H_0 + a;
                H_1 <= H_1 + b;
                H_2 <= H_2 + c;
            end 
                
        end
                
    end
endmodule

// module for_loop (output reg [15:0] for_out);
// // Integer, no es un cable que se sintetiza, es simplemente para la iteración del for loop
// integer i = 0;
// always @ (*) begin
// 	// Valor por defecto
// 	for_out = 'b0;
// 	// For loop utilizado para escribir menos líneas
// 	// y a la vez que la cantidad de líneas las determine el for loop.
// 	for(i = 0; i < 4; i = i + 1) begin
// 		// Indexación por partes, a la izquierda del "+:" el bit inicial,
// 		// a la derecha del "+:" el tamaño del bus. En el ejemplo, cuando i=0,
// 		// for_out [4*0 +: 4] = 0; es igual a for_out [3:0] = 0; con 3=0+(4-1)
// 		// con i=1, for_out [4*1 +: 4] = 4'd1; es igual a for_out [7:4] = 1; con 7=4+(4-1)
// 		for_out [4*i +: 4] = i;
// 	end
// end
// endmodule

RTL/Verificar_módulos/generador_nonce/clock.v
`timescale 1ns / 1ps
module clock (clk);

output clk;
reg clk;

initial begin
clk = 0;
end

always begin
 #100 clk = !clk;
end

endmodule

RTL/Verificar_módulos/micro_ucr_hash/tbtop.v
// `include "clock.v"

// `include "CMOS/cmos_cells.v"
`include "probador.v"
`include "clock.v"
`include "micro_ucr_hash.v"


module tbtop;
/*AUTOWIRE*/
// Beginning of automatic wires (for undeclared instantiated-module outputs)
wire [23:0]		H;			// From hash of micro_ucr_hash.v, ...
wire [127:0]		bloque_in;		// From tb of probador.v
wire			clk;			// From reloj of clock.v
wire			fill;			// From tb of probador.v
wire			reset_L;		// From tb of probador.v
// End of automatics
   clock reloj (/*AUTOINST*/
		// Outputs
		.clk			(clk));

   micro_ucr_hash hash (/*AUTOINST*/
			// Outputs
			.H		(H[23:0]),
			// Inputs
			.clk		(clk),
			.reset_L	(reset_L),
			.bloque_in	(bloque_in[127:0]),
			.fill		(fill));
   
    probador tb (/*AUTOINST*/
		 // Outputs
		 .reset_L		(reset_L),
		 .fill			(fill),
		 .bloque_in		(bloque_in[127:0]),
		 // Inputs
		 .clk			(clk),
		 .H			(H[23:0]));



 
endmodule

RTL/Verificar_módulos/micro_ucr_hash/test.vcd
$date
	Tue Jul 13 10:52:45 2021
$end
$version
	Icarus Verilog
$end
$timescale
	1ps
$end
$scope module tbtop $end
$var wire 1 ! reset_L $end
$var wire 1 " fill $end
$var wire 1 # clk $end
$var wire 128 $ bloque_in [127:0] $end
$var wire 24 % H [23:0] $end
$scope module hash $end
$var wire 1 ! reset_L $end
$var wire 1 " fill $end
$var wire 1 # clk $end
$var wire 128 & bloque_in [127:0] $end
$var reg 24 ' H [23:0] $end
$var reg 8 ( H_0 [7:0] $end
$var reg 8 ) H_1 [7:0] $end
$var reg 8 * H_2 [7:0] $end
$var reg 8 + a [7:0] $end
$var reg 8 , b [7:0] $end
$var reg 8 - c [7:0] $end
$var reg 7 . count [6:0] $end
$var reg 8 / k [7:0] $end
$var reg 8 0 x [7:0] $end
$upscope $end
$scope module reloj $end
$var reg 1 # clk $end
$upscope $end
$scope module tb $end
$var wire 24 1 H [23:0] $end
$var wire 1 # clk $end
$var reg 128 2 bloque_in [127:0] $end
$var reg 1 " fill $end
$var reg 1 ! reset_L $end
$scope task drv_init $end
$upscope $end
$upscope $end
$upscope $end
$enddefinitions $end
#0
$dumpvars
bx 2
bx 1
bx 0
bx /
bx .
bx -
bx ,
bx +
bx *
bx )
bx (
bx '
bx &
bx %
bx $
0#
x"
x!
$end
#100000
0!
1#
#200000
0#
#300000
b111001011111011001111100101111010000001100101010011110011011000110101100011111001100110010010011111101111011011000011100111100 $
b111001011111011001111100101111010000001100101010011110011011000110101100011111001100110010010011111101111011011000011100111100 &
b111001011111011001111100101111010000001100101010011110011011000110101100011111001100110010010011111101111011011000011100111100 2
b0 .
b10011001 /
b11111110 -
b10001001 ,
b1 +
b11111110 *
b10001001 )
b1 (
b0 %
b0 '
b0 1
1#
#400000
0#
#500000
b10001000 0
1!
1#
#600000
0#
#700000
b1 .
b1011101 -
b11100000 ,
b1110111 +
1#
#800000
0#
#900000
b10 .
b10101000 -
b11010000 ,
b10111101 +
b10010111 0
1#
#1000000
0#
#1100000
b11 .
b11101 -
b10000000 ,
b1111000 +
b1101101 0
1#
#1200000
0#
#1300000
b100 .
b11 -
b11010000 ,
b10011101 +
b11111000 0
1#
#1400000
0#
#1500000
b101 .
b10110101 -
b110000 ,
b11010011 +
b1001101 0
1#
#1600000
0#
#1700000
b110 .
b11001 -
b1010000 ,
b10000101 +
b11100011 0
1#
#1800000
0#
#1900000
b111 .
b10011011 -
b10010000 ,
b1001001 +
b11010101 0
1#
#2000000
0#
#2100000
b1000 .
b11011001 -
b10110000 ,
b1011 +
b11011001 0
1#
#2200000
0#
#2300000
b1001 .
b11011110 -
b10010000 ,
b1101001 +
b10111011 0
1#
#2400000
0#
#2500000
b1010 .
b11110010 -
b11100000 ,
b1001110 +
b11111001 0
1#
#2600000
0#
#2700000
b1011 .
b1011100 -
b100000 ,
b10010 +
b10101110 0
1#
#2800000
0#
#2900000
b1100 .
b10000111 -
b11000000 ,
b1111100 +
b110010 0
1#
#3000000
0#
#3100000
b1101 .
b11111010 -
b1110000 ,
b1000111 +
b10111100 0
1#
#3200000
0#
#3300000
b1110 .
b11110100 -
b10100000 ,
b10001010 +
b110111 0
1#
#3400000
0#
#3500000
b1111 .
b1001101 -
b1000000 ,
b1010100 +
b101010 0
1#
#3600000
0#
#3700000
b10000 .
b11111100 -
b11010000 ,
b1101 +
b10100 0
1#
#3800000
0#
#3900000
b10001 .
b1001100 -
b11000000 ,
b101100 +
b11011101 0
1#
#4000000
0#
#4100000
b10010 .
b1110011 -
b10001100 +
b11101100 0
b10100001 /
1#
#4200000
0#
#4300000
b10011 .
b1001000 -
b110000 ,
b10110011 +
b11001100 0
1#
#4400000
0#
#4500000
b10100 .
b1101100 -
b10000000 ,
b1111000 +
b10110011 0
1#
#4600000
0#
#4700000
b10101 .
b1010011 -
b11000000 ,
b11101100 +
b11111000 0
1#
#4800000
0#
#4900000
b10110 .
b10011000 -
b110000 ,
b10010011 +
b11101100 0
1#
#5000000
0#
#5100000
b10111 .
b10001100 -
b10000000 ,
b10101000 +
b10110011 0
1#
#5200000
0#
#5300000
b11000 .
b1010011 -
b11000000 ,
b1100 +
b10101000 0
1#
#5400000
0#
#5500000
b11001 .
b1001000 -
b110000 ,
b10010011 +
b11001100 0
1#
#5600000
0#
#5700000
b11010 .
b1101100 -
b10000000 ,
b1111000 +
b10110011 0
1#
#5800000
0#
#5900000
b11011 .
b1010011 -
b11000000 ,
b11101100 +
b11111000 0
1#
#6000000
0#
#6100000
b11100 .
b10011000 -
b110000 ,
b10010011 +
b11101100 0
1#
#6200000
0#
#6300000
b11101 .
b10001100 -
b10000000 ,
b10101000 +
b10110011 0
1#
#6400000
0#
#6500000
b11110 .
b1010011 -
b11000000 ,
b1100 +
b10101000 0
1#
#6600000
0#
#6700000
b11111 .
b1001000 -
b110000 ,
b10010011 +
b11001100 0
1#
#6800000
0#
#6900000
b100000 .
b1101100 -
b10000000 ,
b1111000 +
b10110011 0
1#
#7000000
0#
#7100000
b1101010 *
b1001 )
b1111001 (
b11000100111111110 %
b11000100111111110 '
b11000100111111110 1
1#
#7200000
0#
#7300000
b11010110 *
b10001001 )
b11110001 (
b11110010000100101101010 %
b11110010000100101101010 '
b11110010000100101101010 1
1#
#7400000
0#
#7500000
b1000010 *
b1001 )
b1101001 (
b111100011000100111010110 %
b111100011000100111010110 '
b111100011000100111010110 1
1#
#7600000
0#
#7700000
b10101110 *
b10001001 )
b11100001 (
b11010010000100101000010 %
b11010010000100101000010 '
b11010010000100101000010 1
1#
#7800000
0#
#7900000
b11010 *
b1001 )
b1011001 (
b111000011000100110101110 %
b111000011000100110101110 '
b111000011000100110101110 1
1#
#8000000
0#
#8100000
b10000110 *
b10001001 )
b11010001 (
b10110010000100100011010 %
b10110010000100100011010 '
b10110010000100100011010 1
1#
#8200000
0#
#8300000
b11110010 *
b1001 )
b1001001 (
b110100011000100110000110 %
b110100011000100110000110 '
b110100011000100110000110 1
1#
#8400000
0#
#8500000
b1011110 *
b10001001 )
b11000001 (
b10010010000100111110010 %
b10010010000100111110010 '
b10010010000100111110010 1
1#
#8600000
0#
#8700000
b11001010 *
b1001 )
b111001 (
b110000011000100101011110 %
b110000011000100101011110 '
b110000011000100101011110 1
1#
#8800000
0#
#8900000
b110110 *
b10001001 )
b10110001 (
b1110010000100111001010 %
b1110010000100111001010 '
b1110010000100111001010 1
1#
#9000000
0#
#9100000
b10100010 *
b1001 )
b101001 (
b101100011000100100110110 %
b101100011000100100110110 '
b101100011000100100110110 1
1#
#9200000
0#
#9300000
b1110 *
b10001001 )
b10100001 (
b1010010000100110100010 %
b1010010000100110100010 '
b1010010000100110100010 1
1#
#9400000
0#
#9500000
b1111010 *
b1001 )
b11001 (
b101000011000100100001110 %
b101000011000100100001110 '
b101000011000100100001110 1
1#
#9600000
0#
#9700000
b11100110 *
b10001001 )
b10010001 (
b110010000100101111010 %
b110010000100101111010 '
b110010000100101111010 1
1#
#9800000
0#
#9900000
b1010010 *
b1001 )
b1001 (
b100100011000100111100110 %
b100100011000100111100110 '
b100100011000100111100110 1
1#
#10000000
0#
#10100000
b10111110 *
b10001001 )
b10000001 (
b10010000100101010010 %
b10010000100101010010 '
b10010000100101010010 1
1#
#10200000
0#
#10300000
b101010 *
b1001 )
b11111001 (
b100000011000100110111110 %
b100000011000100110111110 '
b100000011000100110111110 1
1#
#10400000
0#
#10500000
b10010110 *
b10001001 )
b1110001 (
b111110010000100100101010 %
b111110010000100100101010 '
b111110010000100100101010 1
1#
#10600000
0#
#10700000
b10 *
b1001 )
b11101001 (
b11100011000100110010110 %
b11100011000100110010110 '
b11100011000100110010110 1
1#
